Metadata-Version: 2.1
Name: llm_docstring_generator
Version: 1.0
Summary: Code to generate docstrings for Python code using GPT-4 etc.
Home-page: https://github.com/maxjeblick/llm-docstring-generator.git
Author: Maximilian Jeblick
Classifier: Development Status :: 3 - Alpha
Classifier: Intended Audience :: Developers
Classifier: Programming Language :: Python :: 3.10
License-File: LICENSE
Requires-Dist: annotated-types ==0.6.0
Requires-Dist: anyio ==4.3.0
Requires-Dist: asttokens ==2.4.1
Requires-Dist: astunparse ==1.6.3
Requires-Dist: black ==23.7.0
Requires-Dist: certifi ==2024.2.2
Requires-Dist: charset-normalizer ==3.3.2
Requires-Dist: click ==8.1.7
Requires-Dist: code2flow ==2.5.1
Requires-Dist: coverage ==7.2.7
Requires-Dist: cramjam ==2.8.3
Requires-Dist: decorator ==5.1.1
Requires-Dist: distro ==1.9.0
Requires-Dist: exceptiongroup ==1.2.0
Requires-Dist: executing ==2.0.1
Requires-Dist: Faker ==24.1.0
Requires-Dist: fastparquet ==2024.2.0
Requires-Dist: filelock ==3.13.3
Requires-Dist: fire ==0.6.0
Requires-Dist: flake8 ==6.1.0
Requires-Dist: flake8-black ==0.3.6
Requires-Dist: flake8-isort ==6.0.0
Requires-Dist: fsspec ==2024.3.1
Requires-Dist: greenlet ==3.0.3
Requires-Dist: h11 ==0.14.0
Requires-Dist: httpcore ==1.0.5
Requires-Dist: httpx ==0.27.0
Requires-Dist: huggingface-hub ==0.22.2
Requires-Dist: idna ==3.6
Requires-Dist: iniconfig ==2.0.0
Requires-Dist: ipython ==8.23.0
Requires-Dist: isort ==5.13.2
Requires-Dist: jedi ==0.19.1
Requires-Dist: Jinja2 ==3.1.3
Requires-Dist: joblib ==1.3.2
Requires-Dist: jsonpickle ==3.0.3
Requires-Dist: loguru ==0.7.2
Requires-Dist: MarkupSafe ==2.1.5
Requires-Dist: matplotlib-inline ==0.1.6
Requires-Dist: mccabe ==0.7.0
Requires-Dist: mypy ==1.4.1
Requires-Dist: mypy-extensions ==1.0.0
Requires-Dist: networkx ==3.2.1
Requires-Dist: numpy ==1.26.4
Requires-Dist: openai ==1.12.0
Requires-Dist: packaging ==24.0
Requires-Dist: pandas ==2.2.1
Requires-Dist: parso ==0.8.3
Requires-Dist: pathspec ==0.12.1
Requires-Dist: pexpect ==4.9.0
Requires-Dist: platformdirs ==4.2.0
Requires-Dist: pluggy ==1.4.0
Requires-Dist: prompt-toolkit ==3.0.43
Requires-Dist: ptyprocess ==0.7.0
Requires-Dist: pure-eval ==0.2.2
Requires-Dist: py ==1.11.0
Requires-Dist: pyarrow ==15.0.2
Requires-Dist: pycodestyle ==2.11.1
Requires-Dist: pydantic ==2.6.4
Requires-Dist: pydantic-core ==2.16.3
Requires-Dist: pyflakes ==3.1.0
Requires-Dist: Pygments ==2.17.2
Requires-Dist: pygraphviz ==1.12
Requires-Dist: pytest ==7.4.0
Requires-Dist: pytest-cov ==4.1.0
Requires-Dist: pytest-dependency ==0.5.1
Requires-Dist: pytest-html ==3.2.0
Requires-Dist: pytest-loguru ==0.4.0
Requires-Dist: pytest-metadata ==3.1.1
Requires-Dist: pytest-sugar ==1.0.0
Requires-Dist: python-dateutil ==2.9.0.post0
Requires-Dist: python-dotenv ==1.0.1
Requires-Dist: pytz ==2024.1
Requires-Dist: pyvis ==0.3.1
Requires-Dist: PyYAML ==6.0.1
Requires-Dist: regex ==2023.12.25
Requires-Dist: requests ==2.31.0
Requires-Dist: safetensors ==0.4.2
Requires-Dist: scikit-learn ==1.4.1.post1
Requires-Dist: scipy ==1.12.0
Requires-Dist: six ==1.16.0
Requires-Dist: sniffio ==1.3.1
Requires-Dist: SQLAlchemy ==2.0.29
Requires-Dist: stack-data ==0.6.3
Requires-Dist: termcolor ==2.4.0
Requires-Dist: threadpoolctl ==3.4.0
Requires-Dist: tiktoken ==0.6.0
Requires-Dist: tokenizers ==0.15.2
Requires-Dist: tomli ==2.0.1
Requires-Dist: tqdm ==4.66.2
Requires-Dist: traitlets ==5.14.2
Requires-Dist: transformers ==4.37.1
Requires-Dist: types-tqdm ==4.66.0.20240106
Requires-Dist: typing-extensions ==4.10.0
Requires-Dist: tzdata ==2024.1
Requires-Dist: urllib3 ==2.2.1
Requires-Dist: wcwidth ==0.2.13
